visual_swarm/__init__.py
visual_swarm/pso.py
visual_swarm-0.1.5.dist-info/licenses/LICENSE
visual_swarm-0.1.5.dist-info/METADATA
visual_swarm-0.1.5.dist-info/WHEEL
visual_swarm-0.1.5.dist-info/top_level.txt
visual_swarm-0.1.5.dist-info/RECORD
