Metadata-Version: 2.4
Name: visual-swarm
Version: 0.1.5
Summary: A PSO library with a focus on visualization.
Author-email: Anshul Patil <Aaprocks29@gmail.com>
License: MIT License
Project-URL: Homepage, https://github.com/AnshulPatil29/visual-swarm
Project-URL: Repository, https://github.com/AnshulPatil29/visual-swarm
Project-URL: Bug Tracker, https://github.com/AnshulPatil29/visual-swarm/issues
Classifier: Programming Language :: Python :: 3
Classifier: Operating System :: OS Independent
Requires-Python: >=3.8
License-File: LICENSE
Requires-Dist: numpy<2,>=1.21
Requires-Dist: matplotlib<4,>=3.5
Provides-Extra: gif
Requires-Dist: Pillow>=9.0; extra == "gif"
Dynamic: license-file
